setup.py
class_files/class_files.py
class_files_rt56.egg-info/PKG-INFO
class_files_rt56.egg-info/SOURCES.txt
class_files_rt56.egg-info/dependency_links.txt
class_files_rt56.egg-info/not-zip-safe
class_files_rt56.egg-info/top_level.txt