Metadata-Version: 2.1
Name: class-files-rt56
Version: 0.4
Summary: Удобный класс для работы с файлами.
Author-email: BusinessJson6@gmail.com
